[
    {
        "": "12",
        "Date": "2004-03-31",
        "Auto Capex": "2631.0",
        "Retail: Changes in Inventory": "-372.0",
        "Manufacturing Workforce": "3314.0",
        "Manufacturing Vacancy Ratio": "1.8666666666666665",
        "Total Retail Sales": "98782964.0",
        "Other Sales": "11763012.0",
        "Auto Imports": "9741",
        "Auto Exports": "6297",
        "Change in Retail Inventory %": "1.003765831525363",
        "Average Auto Demand": "11807309.521422824",
        "Auto Demand %": "",
        "Auto Workforce": "3252.1386666666667",
        "Auto Workforce Change": "",
        "Auto Capex Change": "",
        "Auto Supply %": "",
        "Output Gap %": "",
        "Output Gap % Mean": "",
        "Output Gap % Stdev": "",
        "Output Gap % Strength": ""
    },
    {
        "": "13",
        "Date": "2004-06-30",
        "Auto Capex": "2991.0",
        "Retail: Changes in Inventory": "-765.0",
        "Manufacturing Workforce": "3290.0",
        "Manufacturing Vacancy Ratio": "2.033333333333333",
        "Total Retail Sales": "99928749.0",
        "Other Sales": "11870143.0",
        "Auto Imports": "9884",
        "Auto Exports": "6490",
        "Change in Retail Inventory %": "1.0076554545879484",
        "Average Auto Demand": "11961014.340688953",
        "Auto Demand %": "",
        "Auto Workforce": "3223.1033333333335",
        "Auto Workforce Change": "",
        "Auto Capex Change": "",
        "Auto Supply %": "",
        "Output Gap %": "",
        "Output Gap % Mean": "",
        "Output Gap % Stdev": "",
        "Output Gap % Strength": ""
    },
    {
        "": "14",
        "Date": "2004-09-30",
        "Auto Capex": "2751.0",
        "Retail: Changes in Inventory": "553.0",
        "Manufacturing Workforce": "3238.0",
        "Manufacturing Vacancy Ratio": "2.1666666666666665",
        "Total Retail Sales": "100833786.0",
        "Other Sales": "11869988.0",
        "Auto Imports": "9846",
        "Auto Exports": "6562",
        "Change in Retail Inventory %": "0.994515727099645",
        "Average Auto Demand": "11804889.74648406",
        "Auto Demand %": "",
        "Auto Workforce": "3167.8433333333337",
        "Auto Workforce Change": "",
        "Auto Capex Change": "",
        "Auto Supply %": "",
        "Output Gap %": "",
        "Output Gap % Mean": "",
        "Output Gap % Stdev": "",
        "Output Gap % Strength": ""
    },
    {
        "": "15",
        "Date": "2004-12-31",
        "Auto Capex": "2806.0",
        "Retail: Changes in Inventory": "285.0",
        "Manufacturing Workforce": "3207.0",
        "Manufacturing Vacancy Ratio": "2.1",
        "Total Retail Sales": "100527478.0",
        "Other Sales": "11708252.0",
        "Auto Imports": "10008",
        "Auto Exports": "6675",
        "Change in Retail Inventory %": "0.9971649542426599",
        "Average Auto Demand": "11675058.569841532",
        "Auto Demand %": "-0.003677701728994324",
        "Auto Workforce": "3139.653",
        "Auto Workforce Change": "-0.03497194437942952",
        "Auto Capex Change": "0.02090051355547584",
        "Auto Supply %": "-0.0070357154119768395",
        "Output Gap %": "",
        "Output Gap % Mean": "",
        "Output Gap % Stdev": "",
        "Output Gap % Strength": ""
    },
    {
        "": "16",
        "Date": "2005-03-31",
        "Auto Capex": "2854.0",
        "Retail: Changes in Inventory": "-1038.0",
        "Manufacturing Workforce": "3174.0",
        "Manufacturing Vacancy Ratio": "2.066666666666667",
        "Total Retail Sales": "99823608.0",
        "Other Sales": "11639602.0",
        "Auto Imports": "9944",
        "Auto Exports": "6673",
        "Change in Retail Inventory %": "1.010398341843144",
        "Average Auto Demand": "11760634.56051414",
        "Auto Demand %": "-0.005573686974088184",
        "Auto Workforce": "3108.404",
        "Auto Workforce Change": "-0.03599688152255509",
        "Auto Capex Change": "-0.016027140851661237",
        "Auto Supply %": "-0.026012011187108164",
        "Output Gap %": "0.0014620284378886557",
        "Output Gap % Mean": "",
        "Output Gap % Stdev": "",
        "Output Gap % Strength": ""
    },
    {
        "": "17",
        "Date": "2005-06-30",
        "Auto Capex": "3205.0",
        "Retail: Changes in Inventory": "-655.0",
        "Manufacturing Workforce": "3120.0",
        "Manufacturing Vacancy Ratio": "1.9000000000000001",
        "Total Retail Sales": "99879295.0",
        "Other Sales": "11745785.0",
        "Auto Imports": "10144",
        "Auto Exports": "7145",
        "Change in Retail Inventory %": "1.0065579157321844",
        "Average Auto Demand": "11822812.868238356",
        "Auto Demand %": "0.0005395712254256205",
        "Auto Workforce": "3060.72",
        "Auto Workforce Change": "-0.034192262906277415",
        "Auto Capex Change": "0.053976934966115886",
        "Auto Supply %": "0.009892336029919235",
        "Output Gap %": "0.026551582412533786",
        "Output Gap % Mean": "",
        "Output Gap % Stdev": "",
        "Output Gap % Strength": ""
    },
    {
        "": "18",
        "Date": "2005-09-30",
        "Auto Capex": "3009.0",
        "Retail: Changes in Inventory": "717.0",
        "Manufacturing Workforce": "3099.0",
        "Manufacturing Vacancy Ratio": "1.8",
        "Total Retail Sales": "99309914.0",
        "Other Sales": "12067464.0",
        "Auto Imports": "9970",
        "Auto Exports": "7234",
        "Change in Retail Inventory %": "0.9927801770123373",
        "Average Auto Demand": "11980339.046010008",
        "Auto Demand %": "0.00864690511821468",
        "Auto Workforce": "3043.218",
        "Auto Workforce Change": "-0.03101162139493674",
        "Auto Capex Change": "0.02289904117315289",
        "Auto Supply %": "-0.004056290110891925",
        "Output Gap %": "-0.001245430911704556",
        "Output Gap % Mean": "",
        "Output Gap % Stdev": "",
        "Output Gap % Strength": ""
    },
    {
        "": "19",
        "Date": "2005-12-31",
        "Auto Capex": "2961.0",
        "Retail: Changes in Inventory": "292.0",
        "Manufacturing Workforce": "3085.0",
        "Manufacturing Vacancy Ratio": "1.7333333333333334",
        "Total Retail Sales": "99844704.0",
        "Other Sales": "12025156.0",
        "Auto Imports": "10171",
        "Auto Exports": "7193",
        "Change in Retail Inventory %": "0.9970754583037273",
        "Average Auto Demand": "11989987.929873817",
        "Auto Demand %": "0.006472098679931149",
        "Auto Workforce": "3031.5266666666666",
        "Auto Workforce Change": "-0.02490037728529959",
        "Auto Capex Change": "0.01179973533303924",
        "Auto Supply %": "-0.006550320976130175",
        "Output Gap %": "0.010528388790823073",
        "Output Gap % Mean": "",
        "Output Gap % Stdev": "",
        "Output Gap % Strength": ""
    },
    {
        "": "20",
        "Date": "2006-03-31",
        "Auto Capex": "3010.0",
        "Retail: Changes in Inventory": "265.0",
        "Manufacturing Workforce": "3042.0",
        "Manufacturing Vacancy Ratio": "1.8",
        "Total Retail Sales": "101325287.0",
        "Other Sales": "11739851.0",
        "Auto Imports": "10563",
        "Auto Exports": "7322",
        "Change in Retail Inventory %": "0.9973846607510719",
        "Average Auto Demand": "11709147.306903133",
        "Auto Demand %": "-0.0030978725524942",
        "Auto Workforce": "2987.244",
        "Auto Workforce Change": "-0.024167410530139377",
        "Auto Capex Change": "-0.02125340599455039",
        "Auto Supply %": "-0.022710408262344883",
        "Output Gap %": "0.003452448423635975",
        "Output Gap % Mean": "",
        "Output Gap % Stdev": "",
        "Output Gap % Strength": ""
    },
    {
        "": "21",
        "Date": "2006-06-30",
        "Auto Capex": "2856.0",
        "Retail: Changes in Inventory": "-49.0",
        "Manufacturing Workforce": "3025.0",
        "Manufacturing Vacancy Ratio": "1.8",
        "Total Retail Sales": "101930364.0",
        "Other Sales": "11666964.0",
        "Auto Imports": "10614",
        "Auto Exports": "7307",
        "Change in Retail Inventory %": "1.0004807203474717",
        "Average Auto Demand": "11672572.54698802",
        "Auto Demand %": "-0.008580380149049568",
        "Auto Workforce": "2970.5499999999997",
        "Auto Workforce Change": "-0.024037576825852836",
        "Auto Capex Change": "-0.01703786191536749",
        "Auto Supply %": "-0.020537719370610164",
        "Output Gap %": "0.014130028113295315",
        "Output Gap % Mean": "",
        "Output Gap % Stdev": "",
        "Output Gap % Strength": ""
    },
    {
        "": "22",
        "Date": "2006-09-30",
        "Auto Capex": "2999.0",
        "Retail: Changes in Inventory": "-836.0",
        "Manufacturing Workforce": "3018.0",
        "Manufacturing Vacancy Ratio": "1.8",
        "Total Retail Sales": "102147329.0",
        "Other Sales": "11658416.0",
        "Auto Imports": "10659",
        "Auto Exports": "6811",
        "Change in Retail Inventory %": "1.0081842570744066",
        "Average Auto Demand": "11753831.473624375",
        "Auto Demand %": "-0.006528335622288976",
        "Auto Workforce": "2963.676",
        "Auto Workforce Change": "-0.022509859791463138",
        "Auto Capex Change": "0.00430497337713831",
        "Auto Supply %": "-0.009102443207162414",
        "Output Gap %": "0.014009383748321187",
        "Output Gap % Mean": "",
        "Output Gap % Stdev": "",
        "Output Gap % Strength": ""
    },
    {
        "": "23",
        "Date": "2006-12-31",
        "Auto Capex": "2920.0",
        "Retail: Changes in Inventory": "1.0",
        "Manufacturing Workforce": "2999.0",
        "Manufacturing Vacancy Ratio": "1.8",
        "Total Retail Sales": "103636835.0",
        "Other Sales": "11912670.0",
        "Auto Imports": "10478",
        "Auto Exports": "6872",
        "Change in Retail Inventory %": "0.9999903509210794",
        "Average Auto Demand": "11912555.053707015",
        "Auto Demand %": "0.005780635807613048",
        "Auto Workforce": "2945.018",
        "Auto Workforce Change": "-0.014198038225621046",
        "Auto Capex Change": "-0.010152284263959421",
        "Auto Supply %": "-0.012175161244790234",
        "Output Gap %": "0.014883079014775463",
        "Output Gap % Mean": "",
        "Output Gap % Stdev": "",
        "Output Gap % Strength": ""
    },
    {
        "": "24",
        "Date": "2007-03-31",
        "Auto Capex": "3139.0",
        "Retail: Changes in Inventory": "-326.0",
        "Manufacturing Workforce": "2988.0",
        "Manufacturing Vacancy Ratio": "2.0",
        "Total Retail Sales": "104369811.0",
        "Other Sales": "12012332.0",
        "Auto Imports": "11392",
        "Auto Exports": "7245",
        "Change in Retail Inventory %": "1.0031235085785486",
        "Average Auto Demand": "12049852.622050373",
        "Auto Demand %": "0.010663654692038227",
        "Auto Workforce": "2928.24",
        "Auto Workforce Change": "-0.01430668849153549",
        "Auto Capex Change": "0.0322507122507123",
        "Auto Supply %": "0.008972011879588404",
        "Output Gap %": "0.02283881593682846",
        "Output Gap % Mean": "",
        "Output Gap % Stdev": "",
        "Output Gap % Strength": ""
    },
    {
        "": "25",
        "Date": "2007-06-30",
        "Auto Capex": "2983.0",
        "Retail: Changes in Inventory": "-103.0",
        "Manufacturing Workforce": "2985.0",
        "Manufacturing Vacancy Ratio": "1.9666666666666668",
        "Total Retail Sales": "104991459.0",
        "Other Sales": "12169393.0",
        "Auto Imports": "11638",
        "Auto Exports": "7605",
        "Change in Retail Inventory %": "1.000981032180913",
        "Average Auto Demand": "12181331.566155177",
        "Auto Demand %": "0.011980228805895813",
        "Auto Workforce": "2926.2949999999996",
        "Auto Workforce Change": "-0.01265686041665659",
        "Auto Capex Change": "-0.0017663943475381139",
        "Auto Supply %": "-0.007211627382097352",
        "Output Gap %": "0.0030082169263074086",
        "Output Gap % Mean": "0.010961854089270476",
        "Output Gap % Stdev": "0.009296991895500262",
        "Output Gap % Strength": "-0.8555065178461243"
    },
    {
        "": "26",
        "Date": "2007-09-30",
        "Auto Capex": "3006.0",
        "Retail: Changes in Inventory": "-255.0",
        "Manufacturing Workforce": "2973.0",
        "Manufacturing Vacancy Ratio": "2.066666666666667",
        "Total Retail Sales": "105334544.0",
        "Other Sales": "12178301.0",
        "Auto Imports": "11392",
        "Auto Exports": "7883",
        "Change in Retail Inventory %": "1.0024208582514014",
        "Average Auto Demand": "12207782.940463899",
        "Auto Demand %": "0.00820272275221634",
        "Auto Workforce": "2911.558",
        "Auto Workforce Change": "-0.011397361400791506",
        "Auto Capex Change": "0.009511170095111598",
        "Auto Supply %": "-0.0009430956528399537",
        "Output Gap %": "0.015414350134313692",
        "Output Gap % Mean": "0.012357086258912981",
        "Output Gap % Stdev": "0.008743364660621207",
        "Output Gap % Strength": "0.34966674662103087"
    },
    {
        "": "27",
        "Date": "2007-12-31",
        "Auto Capex": "3182.0",
        "Retail: Changes in Inventory": "96.0",
        "Manufacturing Workforce": "2931.0",
        "Manufacturing Vacancy Ratio": "2.2",
        "Total Retail Sales": "104877237.0",
        "Other Sales": "12241522.0",
        "Auto Imports": "11076",
        "Auto Exports": "7952",
        "Change in Retail Inventory %": "0.999084644077723",
        "Average Auto Demand": "12230316.650339616",
        "Auto Demand %": "0.004976188402326202",
        "Auto Workforce": "2866.518",
        "Auto Workforce Change": "-0.021169663467602406",
        "Auto Capex Change": "0.00471078001752856",
        "Auto Supply %": "-0.008229441725036923",
        "Output Gap %": "0.005919284055166156",
        "Output Gap % Mean": "0.010293856423176217",
        "Output Gap % Stdev": "0.007344009145071666",
        "Output Gap % Strength": "-0.5956654303658785"
    },
    {
        "": "28",
        "Date": "2008-03-31",
        "Auto Capex": "3155.0",
        "Retail: Changes in Inventory": "1599.0",
        "Manufacturing Workforce": "2907.0",
        "Manufacturing Vacancy Ratio": "2.2",
        "Total Retail Sales": "113043985.0",
        "Other Sales": "13537873.0",
        "Auto Imports": "11642",
        "Auto Exports": "8688",
        "Change in Retail Inventory %": "0.9858550634073985",
        "Average Auto Demand": "13346380.644816307",
        "Auto Demand %": "0.03175706934734109",
        "Auto Workforce": "2843.046",
        "Auto Workforce Change": "-0.028693773583135407",
        "Auto Capex Change": "0.01875477047214047",
        "Auto Supply %": "-0.004969501555497469",
        "Output Gap %": "0.039986511072378016",
        "Output Gap % Mean": "0.014417050621584476",
        "Output Gap % Stdev": "0.010872501076099262",
        "Output Gap % Strength": "2.351755154754799"
    },
    {
        "": "29",
        "Date": "2008-06-30",
        "Auto Capex": "3178.0",
        "Retail: Changes in Inventory": "823.0",
        "Manufacturing Workforce": "2884.0",
        "Manufacturing Vacancy Ratio": "2.1",
        "Total Retail Sales": "104293232.0",
        "Other Sales": "12652838.0",
        "Auto Imports": "11254",
        "Auto Exports": "8188",
        "Change in Retail Inventory %": "0.9921087880371758",
        "Average Auto Demand": "12552991.773410724",
        "Auto Demand %": "0.011217915084156408",
        "Auto Workforce": "2823.436",
        "Auto Workforce Change": "-0.03055524435731971",
        "Auto Capex Change": "0.018409504441828206",
        "Auto Supply %": "-0.006072869957745752",
        "Output Gap %": "0.016187416639653875",
        "Output Gap % Mean": "0.014982953406467556",
        "Output Gap % Stdev": "0.01079460545433354",
        "Output Gap % Strength": "0.11158010714535024"
    },
    {
        "": "30",
        "Date": "2008-09-30",
        "Auto Capex": "3221.0",
        "Retail: Changes in Inventory": "-613.0",
        "Manufacturing Workforce": "2848.0",
        "Manufacturing Vacancy Ratio": "1.8666666666666665",
        "Total Retail Sales": "102928754.0",
        "Other Sales": "12476797.0",
        "Auto Imports": "9688",
        "Auto Exports": "7798",
        "Change in Retail Inventory %": "1.0059555758345233",
        "Average Auto Demand": "12551103.510705452",
        "Auto Demand %": "0.010552491361140004",
        "Auto Workforce": "2794.8373333333334",
        "Auto Workforce Change": "-0.025214892905747743",
        "Auto Capex Change": "0.004098791382028288",
        "Auto Supply %": "-0.010558050761859727",
        "Output Gap %": "0.016625361318885756",
        "Output Gap % Mean": "0.016300244695992533",
        "Output Gap % Stdev": "0.010006131217129009",
        "Output Gap % Strength": "0.03249174089748814"
    },
    {
        "": "31",
        "Date": "2008-12-31",
        "Auto Capex": "3321.0",
        "Retail: Changes in Inventory": "-2259.0",
        "Manufacturing Workforce": "2694.0",
        "Manufacturing Vacancy Ratio": "1.5",
        "Total Retail Sales": "102543466.0",
        "Other Sales": "12210234.0",
        "Auto Imports": "7210",
        "Auto Exports": "6135",
        "Change in Retail Inventory %": "1.022029682515315",
        "Average Auto Demand": "12479221.578457706",
        "Auto Demand %": "-0.02177451943888664",
        "Auto Workforce": "2653.59",
        "Auto Workforce Change": "-0.06756522113115015",
        "Auto Capex Change": "0.01737492149884856",
        "Auto Supply %": "-0.025095149816150797",
        "Output Gap %": "-0.011216468677026914",
        "Output Gap % Mean": "0.01376559501696031",
        "Output Gap % Stdev": "0.013288755239309766",
        "Output Gap % Strength": "-1.8799400879991544"
    },
    {
        "": "32",
        "Date": "2009-03-31",
        "Auto Capex": "3007.0",
        "Retail: Changes in Inventory": "-504.0",
        "Manufacturing Workforce": "2689.0",
        "Manufacturing Vacancy Ratio": "1.1666666666666667",
        "Total Retail Sales": "103079249.0",
        "Other Sales": "11977319.0",
        "Auto Imports": "6147",
        "Auto Exports": "4554",
        "Change in Retail Inventory %": "1.0048894419089143",
        "Average Auto Demand": "12035881.405475035",
        "Auto Demand %": "-0.013801277320860192",
        "Auto Workforce": "2657.628333333333",
        "Auto Workforce Change": "-0.05914585168766007",
        "Auto Capex Change": "-0.017592592592592604",
        "Auto Supply %": "-0.038369222140126336",
        "Output Gap %": "0.011293872495290605",
        "Output Gap % Mean": "0.013494043891657254",
        "Output Gap % Stdev": "0.013310946712447707",
        "Output Gap % Strength": "-0.16529037670244465"
    },
    {
        "": "33",
        "Date": "2009-06-30",
        "Auto Capex": "2766.0",
        "Retail: Changes in Inventory": "434.0",
        "Manufacturing Workforce": "2657.0",
        "Manufacturing Vacancy Ratio": "1.1",
        "Total Retail Sales": "103862316.0",
        "Other Sales": "11995281.0",
        "Auto Imports": "6792",
        "Auto Exports": "4877",
        "Change in Retail Inventory %": "0.9958213910808613",
        "Average Auto Demand": "11945157.411825825",
        "Auto Demand %": "-0.016263734186493184",
        "Auto Workforce": "2627.773",
        "Auto Workforce Change": "-0.06025064778895961",
        "Auto Capex Change": "-0.04764896847837474",
        "Auto Supply %": "-0.053949808133667176",
        "Output Gap %": "0.02210548795363315",
        "Output Gap % Mean": "0.01421628478554302",
        "Output Gap % Stdev": "0.013587751643814597",
        "Output Gap % Strength": "0.5806113752219961"
    },
    {
        "": "34",
        "Date": "2009-09-30",
        "Auto Capex": "2642.0",
        "Retail: Changes in Inventory": "1032.0",
        "Manufacturing Workforce": "2639.0",
        "Manufacturing Vacancy Ratio": "1.1",
        "Total Retail Sales": "104534063.0",
        "Other Sales": "12131096.0",
        "Auto Imports": "8515",
        "Auto Exports": "5860",
        "Change in Retail Inventory %": "0.9901276199318877",
        "Average Auto Demand": "12011333.209645243",
        "Auto Demand %": "-0.012508031156077496",
        "Auto Workforce": "2609.971",
        "Auto Workforce Change": "-0.016486545708049527",
        "Auto Capex Change": "-0.07466461403122937",
        "Auto Supply %": "-0.04557557986963945",
        "Output Gap %": "0.04144177697758968",
        "Output Gap % Mean": "0.016076580889619142",
        "Output Gap % Stdev": "0.015964945343198273",
        "Output Gap % Strength": "1.5888056953967062"
    },
    {
        "": "35",
        "Date": "2009-12-31",
        "Auto Capex": "2585.0",
        "Retail: Changes in Inventory": "610.0",
        "Manufacturing Workforce": "2621.0",
        "Manufacturing Vacancy Ratio": "1.1666666666666667",
        "Total Retail Sales": "103863701.0",
        "Other Sales": "12166918.0",
        "Auto Imports": "9369",
        "Auto Exports": "6771",
        "Change in Retail Inventory %": "0.9941269183157646",
        "Average Auto Demand": "12095460.696740607",
        "Auto Demand %": "0.001668727950619305",
        "Auto Workforce": "2590.4216666666666",
        "Auto Workforce Change": "-0.025498632672816934",
        "Auto Capex Change": "-0.05014854426619131",
        "Auto Supply %": "-0.03782358846950412",
        "Output Gap %": "0.047244307820258756",
        "Output Gap % Mean": "0.020500189979014278",
        "Output Gap % Stdev": "0.017947074072546743",
        "Output Gap % Strength": "1.490165902984397"
    },
    {
        "": "36",
        "Date": "2010-03-31",
        "Auto Capex": "2731.0",
        "Retail: Changes in Inventory": "-1822.0",
        "Manufacturing Workforce": "2572.0",
        "Manufacturing Vacancy Ratio": "1.1666666666666667",
        "Total Retail Sales": "101873241.0",
        "Other Sales": "11668242.0",
        "Auto Imports": "9353",
        "Auto Exports": "6277",
        "Change in Retail Inventory %": "1.0178849713832114",
        "Average Auto Demand": "11876928.174262386",
        "Auto Demand %": "-0.001841113071641846",
        "Auto Workforce": "2541.9933333333333",
        "Auto Workforce Change": "-0.03295996154618719",
        "Auto Capex Change": "-0.0043788314775428105",
        "Auto Supply %": "-0.018669396511865",
        "Output Gap %": "0.03598247539786228",
        "Output Gap % Mean": "0.022557002505369135",
        "Output Gap % Stdev": "0.018470420277563144",
        "Output Gap % Strength": "0.7268634222038615"
    },
    {
        "": "37",
        "Date": "2010-06-30",
        "Auto Capex": "2783.0",
        "Retail: Changes in Inventory": "-970.0",
        "Manufacturing Workforce": "2570.0",
        "Manufacturing Vacancy Ratio": "1.2333333333333334",
        "Total Retail Sales": "103173948.0",
        "Other Sales": "11916343.0",
        "Auto Imports": "9545",
        "Auto Exports": "7300",
        "Change in Retail Inventory %": "1.0094015981631332",
        "Average Auto Demand": "12028375.668460065",
        "Auto Demand %": "0.000562698277557098",
        "Auto Workforce": "2538.3033333333333",
        "Auto Workforce Change": "-0.027637020484509667",
        "Auto Capex Change": "0.017718019602915414",
        "Auto Supply %": "-0.004959500440797127",
        "Output Gap %": "0.0192320947894221",
        "Output Gap % Mean": "0.02388828357879473",
        "Output Gap % Stdev": "0.01759711488409099",
        "Output Gap % Strength": "-0.2645995562364686"
    },
    {
        "": "38",
        "Date": "2010-09-30",
        "Auto Capex": "2787.0",
        "Retail: Changes in Inventory": "339.0",
        "Manufacturing Workforce": "2565.0",
        "Manufacturing Vacancy Ratio": "1.3999999999999997",
        "Total Retail Sales": "103120952.0",
        "Other Sales": "12378182.0",
        "Auto Imports": "9226",
        "Auto Exports": "7711",
        "Change in Retail Inventory %": "0.9967125982312498",
        "Average Auto Demand": "12337489.942599287",
        "Auto Demand %": "0.0067942800999992725",
        "Auto Workforce": "2529.09",
        "Auto Workforce Change": "-0.023776492396871185",
        "Auto Capex Change": "0.024941350784047467",
        "Auto Supply %": "0.0005824291935881409",
        "Output Gap %": "0.011753780540796399",
        "Output Gap % Mean": "0.021065010525636568",
        "Output Gap % Stdev": "0.01698139700578322",
        "Output Gap % Strength": "-0.5483194334169984"
    },
    {
        "": "39",
        "Date": "2010-12-31",
        "Auto Capex": "2717.0",
        "Retail: Changes in Inventory": "2189.0",
        "Manufacturing Workforce": "2567.0",
        "Manufacturing Vacancy Ratio": "1.3999999999999997",
        "Total Retail Sales": "101681866.0",
        "Other Sales": "12269245.0",
        "Auto Imports": "9273",
        "Auto Exports": "8041",
        "Change in Retail Inventory %": "0.9784720709197056",
        "Average Auto Demand": "12005113.563771242",
        "Auto Demand %": "0.003836600221980809",
        "Auto Workforce": "2531.062",
        "Auto Workforce Change": "-0.004301610780179543",
        "Auto Capex Change": "-0.0016865437899048485",
        "Auto Supply %": "-0.002994077285042196",
        "Output Gap %": "0.003254171028392668",
        "Output Gap % Mean": "0.019771685964510448",
        "Output Gap % Stdev": "0.01786373979660753",
        "Output Gap % Strength": "-0.9246392482303505"
    },
    {
        "": "40",
        "Date": "2011-03-31",
        "Auto Capex": "2550.0",
        "Retail: Changes in Inventory": "2830.0",
        "Manufacturing Workforce": "2562.0",
        "Manufacturing Vacancy Ratio": "1.5666666666666667",
        "Total Retail Sales": "102032828.0",
        "Other Sales": "11996775.0",
        "Auto Imports": "10044",
        "Auto Exports": "8590",
        "Change in Retail Inventory %": "0.9722638286571847",
        "Average Auto Demand": "11664030.393038798",
        "Auto Demand %": "-0.009884364205087462",
        "Auto Workforce": "2521.862",
        "Auto Workforce Change": "-0.006484831936410362",
        "Auto Capex Change": "-0.028116326776879474",
        "Auto Supply %": "-0.01730057935664492",
        "Output Gap %": "-0.006890286920045266",
        "Output Gap % Mean": "0.017420121140617344",
        "Output Gap % Stdev": "0.01977001563479262",
        "Output Gap % Strength": "-1.2296605379451244"
    },
    {
        "": "41",
        "Date": "2011-06-30",
        "Auto Capex": "2605.0",
        "Retail: Changes in Inventory": "-55.0",
        "Manufacturing Workforce": "2564.0",
        "Manufacturing Vacancy Ratio": "1.6333333333333335",
        "Total Retail Sales": "101707802.0",
        "Other Sales": "11814605.0",
        "Auto Imports": "9723",
        "Auto Exports": "8405",
        "Change in Retail Inventory %": "1.000540764807797",
        "Average Auto Demand": "11820993.922602024",
        "Auto Demand %": "-0.013964929840177054",
        "Auto Workforce": "2522.1213333333335",
        "Auto Workforce Change": "-0.0027522767010015325",
        "Auto Capex Change": "-0.022597467097094648",
        "Auto Supply %": "-0.01267487189904809",
        "Output Gap %": "0.0033356495164678646",
        "Output Gap % Mean": "0.018875332959966823",
        "Output Gap % Stdev": "0.017872459614213465",
        "Output Gap % Strength": "-0.8694764894665469"
    },
    {
        "": "42",
        "Date": "2011-09-30",
        "Auto Capex": "2778.0",
        "Retail: Changes in Inventory": "-799.0",
        "Manufacturing Workforce": "2566.0",
        "Manufacturing Vacancy Ratio": "1.5",
        "Total Retail Sales": "101175429.0",
        "Other Sales": "11636720.0",
        "Auto Imports": "9813",
        "Auto Exports": "8761",
        "Change in Retail Inventory %": "1.0078971743228289",
        "Average Auto Demand": "11728617.20638595",
        "Auto Demand %": "-0.007589688267947851",
        "Auto Workforce": "2527.5099999999998",
        "Auto Workforce Change": "-0.0013954425631437228",
        "Auto Capex Change": "0.007748983739837456",
        "Auto Supply %": "0.0031767705883468667",
        "Output Gap %": "0.005085183631100239",
        "Output Gap % Mean": "0.018254464073547787",
        "Output Gap % Stdev": "0.018268546764404116",
        "Output Gap % Strength": "-0.7208718138493434"
    },
    {
        "": "43",
        "Date": "2011-12-31",
        "Auto Capex": "2775.0",
        "Retail: Changes in Inventory": "-2106.0",
        "Manufacturing Workforce": "2539.0",
        "Manufacturing Vacancy Ratio": "1.5333333333333332",
        "Total Retail Sales": "101911624.0",
        "Other Sales": "11724016.0",
        "Auto Imports": "9948",
        "Auto Exports": "8977",
        "Change in Retail Inventory %": "1.0206649635963019",
        "Average Auto Demand": "11966292.363842461",
        "Auto Demand %": "0.008635658803924104",
        "Auto Workforce": "2500.0686666666666",
        "Auto Workforce Change": "-0.008617666917324351",
        "Auto Capex Change": "0.028362536241018477",
        "Auto Supply %": "0.009872434661847063",
        "Output Gap %": "0.005458888215577237",
        "Output Gap % Mean": "0.016589804099742193",
        "Output Gap % Stdev": "0.01863343367974521",
        "Output Gap % Strength": "-0.5973625728608684"
    },
    {
        "": "44",
        "Date": "2012-03-31",
        "Auto Capex": "3057.0",
        "Retail: Changes in Inventory": "-1072.0",
        "Manufacturing Workforce": "2580.0",
        "Manufacturing Vacancy Ratio": "1.7333333333333334",
        "Total Retail Sales": "102471906.0",
        "Other Sales": "11843789.0",
        "Auto Imports": "10235",
        "Auto Exports": "9595",
        "Change in Retail Inventory %": "1.0104614039286046",
        "Average Auto Demand": "11967691.660774164",
        "Auto Demand %": "0.004188951766417685",
        "Auto Workforce": "2535.28",
        "Auto Workforce Change": "0.005363645501493819",
        "Auto Capex Change": "0.05540573670017168",
        "Auto Supply %": "0.03038469110083275",
        "Output Gap %": "-0.0056834828954293775",
        "Output Gap % Mean": "0.011877278112440288",
        "Output Gap % Stdev": "0.017579165073446153",
        "Output Gap % Strength": "-0.9989530751034196"
    },
    {
        "": "45",
        "Date": "2012-06-30",
        "Auto Capex": "3109.0",
        "Retail: Changes in Inventory": "-329.0",
        "Manufacturing Workforce": "2603.0",
        "Manufacturing Vacancy Ratio": "1.6333333333333335",
        "Total Retail Sales": "101510997.0",
        "Other Sales": "11642624.0",
        "Auto Imports": "9823",
        "Auto Exports": "9309",
        "Change in Retail Inventory %": "1.0032410281617075",
        "Average Auto Demand": "11680358.072260171",
        "Auto Demand %": "-0.001209206568731395",
        "Auto Workforce": "2560.4843333333333",
        "Auto Workforce Change": "0.01316852400390145",
        "Auto Capex Change": "0.03844367015098715",
        "Auto Supply %": "0.0258060970774443",
        "Output Gap %": "-0.03159389766956414",
        "Output Gap % Mean": "0.003993457563458",
        "Output Gap % Stdev": "0.01763397437759118",
        "Output Gap % Strength": "-2.018113130426552"
    },
    {
        "": "46",
        "Date": "2012-09-30",
        "Auto Capex": "3044.0",
        "Retail: Changes in Inventory": "-362.0",
        "Manufacturing Workforce": "2587.0",
        "Manufacturing Vacancy Ratio": "1.5",
        "Total Retail Sales": "102308005.0",
        "Other Sales": "11914052.0",
        "Auto Imports": "9958",
        "Auto Exports": "8943",
        "Change in Retail Inventory %": "1.0035383350501264",
        "Average Auto Demand": "11956207.907780629",
        "Auto Demand %": "-9.187130983945302e-05",
        "Auto Workforce": "2548.195",
        "Auto Workforce Change": "0.019225973442966504",
        "Auto Capex Change": "0.030086120120791815",
        "Auto Supply %": "0.02465604678187916",
        "Output Gap %": "-0.025897968387283754",
        "Output Gap % Mean": "-0.002194586815056603",
        "Output Gap % Stdev": "0.015937010113429757",
        "Output Gap % Strength": "-1.4873167177231599"
    },
    {
        "": "47",
        "Date": "2012-12-31",
        "Auto Capex": "3245.0",
        "Retail: Changes in Inventory": "936.0",
        "Manufacturing Workforce": "2547.0",
        "Manufacturing Vacancy Ratio": "1.5333333333333332",
        "Total Retail Sales": "101999393.0",
        "Other Sales": "11959508.0",
        "Auto Imports": "9914",
        "Auto Exports": "9146",
        "Change in Retail Inventory %": "0.9908234748024431",
        "Average Auto Demand": "11849761.273487618",
        "Auto Demand %": "-0.0030985311921655954",
        "Auto Workforce": "2507.946",
        "Auto Workforce Change": "-0.01065327506900704",
        "Auto Capex Change": "0.020412595005428802",
        "Auto Supply %": "0.004879659968210881",
        "Output Gap %": "-0.027754577974044754",
        "Output Gap % Mean": "-0.006893254091403287",
        "Output Gap % Stdev": "0.01584413787118404",
        "Output Gap % Strength": "-1.3166588205838738"
    },
    {
        "": "48",
        "Date": "2013-03-31",
        "Auto Capex": "3295.0",
        "Retail: Changes in Inventory": "-182.0",
        "Manufacturing Workforce": "2546.0",
        "Manufacturing Vacancy Ratio": "1.5666666666666667",
        "Total Retail Sales": "102091759.0",
        "Other Sales": "11814510.0",
        "Auto Imports": "10669",
        "Auto Exports": "9540",
        "Change in Retail Inventory %": "1.001782710003067",
        "Average Auto Demand": "11835571.845158335",
        "Auto Demand %": "0.0045053563650054125",
        "Auto Workforce": "2506.1126666666664",
        "Auto Workforce Change": "-0.021325724696283244",
        "Auto Capex Change": "0.019791444988295437",
        "Auto Supply %": "-0.0007671398539939034",
        "Output Gap %": "-0.0003743036032054685",
        "Output Gap % Mean": "-0.008106062505803476",
        "Output Gap % Stdev": "0.014679562952631784",
        "Output Gap % Strength": "0.5267022545253529"
    },
    {
        "": "49",
        "Date": "2013-06-30",
        "Auto Capex": "3239.0",
        "Retail: Changes in Inventory": "-126.0",
        "Manufacturing Workforce": "2560.0",
        "Manufacturing Vacancy Ratio": "1.6000000000000003",
        "Total Retail Sales": "102487389.0",
        "Other Sales": "12104041.0",
        "Auto Imports": "10983",
        "Auto Exports": "9187",
        "Change in Retail Inventory %": "1.001229419553268",
        "Average Auto Demand": "12118921.944678959",
        "Auto Demand %": "0.00461335422164133",
        "Auto Workforce": "2519.04",
        "Auto Workforce Change": "-0.011367791019833762",
        "Auto Capex Change": "0.02034641068447418",
        "Auto Supply %": "0.00448930983232021",
        "Output Gap %": "0.005380494075635234",
        "Output Gap % Mean": "-0.00789343020107922",
        "Output Gap % Stdev": "0.01487647768131984",
        "Output Gap % Strength": "0.8922760186292157"
    },
    {
        "": "50",
        "Date": "2013-09-30",
        "Auto Capex": "3390.0",
        "Retail: Changes in Inventory": "355.0",
        "Manufacturing Workforce": "2575.0",
        "Manufacturing Vacancy Ratio": "1.5666666666666667",
        "Total Retail Sales": "103788630.0",
        "Other Sales": "12351102.0",
        "Auto Imports": "11871",
        "Auto Exports": "9633",
        "Change in Retail Inventory %": "0.9965795868005966",
        "Average Auto Demand": "12308856.127692021",
        "Auto Demand %": "0.012805212340946967",
        "Auto Workforce": "2534.6583333333333",
        "Auto Workforce Change": "0.010627424274027075",
        "Auto Capex Change": "0.014827691993046344",
        "Auto Supply %": "0.01272755813353671",
        "Output Gap %": "0.008315902508626757",
        "Output Gap % Mean": "-0.006372811258212016",
        "Output Gap % Stdev": "0.01574236903173817",
        "Output Gap % Strength": "0.9330688244713915"
    },
    {
        "": "51",
        "Date": "2013-12-31",
        "Auto Capex": "3322.0",
        "Retail: Changes in Inventory": "783.0",
        "Manufacturing Workforce": "2576.0",
        "Manufacturing Vacancy Ratio": "1.6666666666666667",
        "Total Retail Sales": "103792062.0",
        "Other Sales": "12530722.0",
        "Auto Imports": "11777",
        "Auto Exports": "10260",
        "Change in Retail Inventory %": "0.9924560704844654",
        "Average Auto Demand": "12436191.116453242",
        "Auto Demand %": "0.016652690289706024",
        "Auto Workforce": "2533.0666666666666",
        "Auto Workforce Change": "0.010730473131982943",
        "Auto Capex Change": "0.0027206771463119672",
        "Auto Supply %": "0.006725575139147455",
        "Output Gap %": "0.003925132156169315",
        "Output Gap % Mean": "-0.006313862994241871",
        "Output Gap % Stdev": "0.01578381140971453",
        "Output Gap % Strength": "0.6487023244657717"
    },
    {
        "": "52",
        "Date": "2014-03-31",
        "Auto Capex": "3525.0",
        "Retail: Changes in Inventory": "-489.0",
        "Manufacturing Workforce": "2580.0",
        "Manufacturing Vacancy Ratio": "1.7",
        "Total Retail Sales": "113212496.0",
        "Other Sales": "13760497.0",
        "Auto Imports": "12271",
        "Auto Exports": "10095",
        "Change in Retail Inventory %": "1.0043193111827513",
        "Average Auto Demand": "13819932.868572315",
        "Auto Demand %": "0.04576161618548946",
        "Auto Workforce": "2536.14",
        "Auto Workforce Change": "0.006785437846137055",
        "Auto Capex Change": "0.02874083006732997",
        "Auto Supply %": "0.017763133956733512",
        "Output Gap %": "0.03903604104634201",
        "Output Gap % Mean": "-0.002918777252717694",
        "Output Gap % Stdev": "0.02122254509859568",
        "Output Gap % Strength": "1.9768985342778655"
    },
    {
        "": "53",
        "Date": "2014-06-30",
        "Auto Capex": "3617.0",
        "Retail: Changes in Inventory": "207.0",
        "Manufacturing Workforce": "2621.0",
        "Manufacturing Vacancy Ratio": "1.9333333333333333",
        "Total Retail Sales": "106464366.0",
        "Other Sales": "12923515.0",
        "Auto Imports": "12863",
        "Auto Exports": "10443",
        "Change in Retail Inventory %": "0.9980556874776298",
        "Average Auto Demand": "12898387.647952462",
        "Auto Demand %": "0.018309998261953342",
        "Auto Workforce": "2570.327333333333",
        "Auto Workforce Change": "0.014065390081846263",
        "Auto Capex Change": "0.022174465175344382",
        "Auto Supply %": "0.018119927628595323",
        "Output Gap %": "0.0005468643052198296",
        "Output Gap % Mean": "-0.003409979643753435",
        "Output Gap % Stdev": "0.021063344619338637",
        "Output Gap % Strength": "0.18785449416900366"
    },
    {
        "": "54",
        "Date": "2014-09-30",
        "Auto Capex": "3728.0",
        "Retail: Changes in Inventory": "345.0",
        "Manufacturing Workforce": "2640.0",
        "Manufacturing Vacancy Ratio": "2.1333333333333333",
        "Total Retail Sales": "106617592.0",
        "Other Sales": "13024420.0",
        "Auto Imports": "12629",
        "Auto Exports": "10133",
        "Change in Retail Inventory %": "0.9967641362599898",
        "Average Auto Demand": "12982274.751587337",
        "Auto Demand %": "0.017029564770807748",
        "Auto Workforce": "2583.68",
        "Auto Workforce Change": "0.01988827959531103",
        "Auto Capex Change": "0.038799694189602496",
        "Auto Supply %": "0.029343986892456764",
        "Output Gap %": "-0.0010903628577875746",
        "Output Gap % Mean": "-0.0029506676399892553",
        "Output Gap % Stdev": "0.021058338303145522",
        "Output Gap % Strength": "0.08834053073996839"
    },
    {
        "": "55",
        "Date": "2014-12-31",
        "Auto Capex": "4102.0",
        "Retail: Changes in Inventory": "411.0",
        "Manufacturing Workforce": "2631.0",
        "Manufacturing Vacancy Ratio": "2.0",
        "Total Retail Sales": "108475382.0",
        "Other Sales": "13531367.0",
        "Auto Imports": "13023",
        "Auto Exports": "10038",
        "Change in Retail Inventory %": "0.9962111218930761",
        "Average Auto Demand": "13480098.299816947",
        "Auto Demand %": "-0.007277409899870209",
        "Auto Workforce": "2578.38",
        "Auto Workforce Change": "0.016623656359348926",
        "Auto Capex Change": "0.05308187672493103",
        "Auto Supply %": "0.03485276654213998",
        "Output Gap %": "-0.036621396792326975",
        "Output Gap % Mean": "-0.0034534175522655383",
        "Output Gap % Stdev": "0.021862800240458013",
        "Output Gap % Strength": "-1.5170965692986904"
    },
    {
        "": "56",
        "Date": "2015-03-31",
        "Auto Capex": "4141.0",
        "Retail: Changes in Inventory": "-725.0",
        "Manufacturing Workforce": "2650.0",
        "Manufacturing Vacancy Ratio": "2.033333333333333",
        "Total Retail Sales": "110016297.0",
        "Other Sales": "13204903.0",
        "Auto Imports": "13785",
        "Auto Exports": "10154",
        "Change in Retail Inventory %": "1.0065899327624162",
        "Average Auto Demand": "13291922.422904227",
        "Auto Demand %": "0.010296853274029552",
        "Auto Workforce": "2596.116666666667",
        "Auto Workforce Change": "0.010022587225374968",
        "Auto Capex Change": "0.04577618590023591",
        "Auto Supply %": "0.02789938656280544",
        "Output Gap %": "-0.02455591326811043",
        "Output Gap % Mean": "-0.003319212040348206",
        "Output Gap % Stdev": "0.02171332325566439",
        "Output Gap % Strength": "-0.9780493284104804"
    },
    {
        "": "57",
        "Date": "2015-06-30",
        "Auto Capex": "4505.0",
        "Retail: Changes in Inventory": "666.0",
        "Manufacturing Workforce": "2641.0",
        "Manufacturing Vacancy Ratio": "1.9333333333333333",
        "Total Retail Sales": "111010256.0",
        "Other Sales": "13290049.0",
        "Auto Imports": "13726",
        "Auto Exports": "10614",
        "Change in Retail Inventory %": "0.9940005543271605",
        "Average Auto Demand": "13210316.073035125",
        "Auto Demand %": "0.006082442044961038",
        "Auto Workforce": "2589.940666666667",
        "Auto Workforce Change": "0.002448720973006413",
        "Auto Capex Change": "0.06490685824074838",
        "Auto Supply %": "0.033677789606877395",
        "Output Gap %": "-0.0218169445178444",
        "Output Gap % Mean": "-0.0027254486947281705",
        "Output Gap % Stdev": "0.021041675869659042",
        "Output Gap % Strength": "-0.9073182165421118"
    },
    {
        "": "58",
        "Date": "2015-09-30",
        "Auto Capex": "4582.0",
        "Retail: Changes in Inventory": "835.0",
        "Manufacturing Workforce": "2620.0",
        "Manufacturing Vacancy Ratio": "2.1",
        "Total Retail Sales": "111559749.0",
        "Other Sales": "13176742.0",
        "Auto Imports": "14273",
        "Auto Exports": "10556",
        "Change in Retail Inventory %": "0.9925152215966352",
        "Average Auto Demand": "13078117.00605169",
        "Auto Demand %": "-0.010035445830143338",
        "Auto Workforce": "2564.98",
        "Auto Workforce Change": "-0.00513748522022317",
        "Auto Capex Change": "0.037652965171007136",
        "Auto Supply %": "0.016257739975391983",
        "Output Gap %": "-0.043713235437020735",
        "Output Gap % Mean": "-0.007059341878109697",
        "Output Gap % Stdev": "0.024656334746481094",
        "Output Gap % Strength": "-1.4865913338616645"
    },
    {
        "": "59",
        "Date": "2015-12-31",
        "Auto Capex": "4556.0",
        "Retail: Changes in Inventory": "297.0",
        "Manufacturing Workforce": "2626.0",
        "Manufacturing Vacancy Ratio": "2.0",
        "Total Retail Sales": "112243426.0",
        "Other Sales": "13129636.0",
        "Auto Imports": "15093",
        "Auto Exports": "10706",
        "Change in Retail Inventory %": "0.997353965300382",
        "Average Auto Demand": "13094894.527550647",
        "Auto Demand %": "-0.004954644896591105",
        "Auto Workforce": "2573.48",
        "Auto Workforce Change": "-0.00870261559756591",
        "Auto Capex Change": "0.031372845479286315",
        "Auto Supply %": "0.011335114940860203",
        "Output Gap %": "-0.021212384871983087",
        "Output Gap % Mean": "-0.00971862977287153",
        "Output Gap % Stdev": "0.024599581239734897",
        "Output Gap % Strength": "-0.46723377065240734"
    },
    {
        "": "60",
        "Date": "2016-03-31",
        "Auto Capex": "4831.0",
        "Retail: Changes in Inventory": "136.0",
        "Manufacturing Workforce": "2636.0",
        "Manufacturing Vacancy Ratio": "1.9333333333333333",
        "Total Retail Sales": "114618214.0",
        "Other Sales": "13726133.0",
        "Auto Imports": "14703",
        "Auto Exports": "10510",
        "Change in Retail Inventory %": "0.9988134521098017",
        "Average Auto Demand": "13709846.285848267",
        "Auto Demand %": "0.012745598129744296",
        "Auto Workforce": "2585.037333333333",
        "Auto Workforce Change": "-0.001832742075348004",
        "Auto Capex Change": "0.023895037748295822",
        "Auto Supply %": "0.011031147836473909",
        "Output Gap %": "0.001410483188884093",
        "Output Gap % Mean": "-0.010409171704845796",
        "Output Gap % Stdev": "0.024129509120663896",
        "Output Gap % Strength": "0.489842326863079"
    },
    {
        "": "61",
        "Date": "2016-06-30",
        "Auto Capex": "4585.0",
        "Retail: Changes in Inventory": "322.0",
        "Manufacturing Workforce": "2655.0",
        "Manufacturing Vacancy Ratio": "1.8666666666666665",
        "Total Retail Sales": "115518616.0",
        "Other Sales": "14272410.0",
        "Auto Imports": "15181",
        "Auto Exports": "11742",
        "Change in Retail Inventory %": "0.997212570483012",
        "Average Auto Demand": "14232626.663087446",
        "Auto Demand %": "0.028791933470427633",
        "Auto Workforce": "2605.44",
        "Auto Workforce Change": "0.015697402135387506",
        "Auto Capex Change": "0.00021476125706931803",
        "Auto Supply %": "0.007956081696228412",
        "Output Gap %": "0.017760785633953724",
        "Output Gap % Mean": "-0.009025606357067357",
        "Output Gap % Stdev": "0.02540566558032099",
        "Output Gap % Strength": "1.0543471851321853"
    },
    {
        "": "62",
        "Date": "2016-09-30",
        "Auto Capex": "4489.0",
        "Retail: Changes in Inventory": "408.0",
        "Manufacturing Workforce": "2626.0",
        "Manufacturing Vacancy Ratio": "2.033333333333333",
        "Total Retail Sales": "117235860.0",
        "Other Sales": "14247065.0",
        "Auto Imports": "15490",
        "Auto Exports": "11136",
        "Change in Retail Inventory %": "0.9965198361661697",
        "Average Auto Demand": "14197482.879648771",
        "Auto Demand %": "0.027541229910035086",
        "Auto Workforce": "2572.6046666666666",
        "Auto Workforce Change": "-0.0002190696895224553",
        "Auto Capex Change": "-0.004795304895505281",
        "Auto Supply %": "-0.0025071872925138683",
        "Output Gap %": "0.019585148213806674",
        "Output Gap % Mean": "-0.010970695640320889",
        "Output Gap % Stdev": "0.021806854669012336",
        "Output Gap % Strength": "1.4012036269287194"
    },
    {
        "": "63",
        "Date": "2016-12-31",
        "Auto Capex": "4124.0",
        "Retail: Changes in Inventory": "269.0",
        "Manufacturing Workforce": "2634.0",
        "Manufacturing Vacancy Ratio": "2.1666666666666665",
        "Total Retail Sales": "118366734.0",
        "Other Sales": "14377128.0",
        "Auto Imports": "16065",
        "Auto Exports": "11371",
        "Change in Retail Inventory %": "0.9977274020249642",
        "Average Auto Demand": "14344454.56802037",
        "Auto Demand %": "0.015338153036138466",
        "Auto Workforce": "2576.9300000000003",
        "Auto Workforce Change": "-0.003028700344357982",
        "Auto Capex Change": "-0.050845019777058575",
        "Auto Supply %": "-0.02693686006070828",
        "Output Gap %": "0.017845340328652336",
        "Output Gap % Mean": "-0.009240848037977636",
        "Output Gap % Stdev": "0.023446478554812477",
        "Output Gap % Strength": "1.1552348171734486"
    },
    {
        "": "64",
        "Date": "2017-03-31",
        "Auto Capex": "4167.0",
        "Retail: Changes in Inventory": "453.0",
        "Manufacturing Workforce": "2649.0",
        "Manufacturing Vacancy Ratio": "2.066666666666667",
        "Total Retail Sales": "116854033.0",
        "Other Sales": "13951032.0",
        "Auto Imports": "16132",
        "Auto Exports": "11542",
        "Change in Retail Inventory %": "0.996123368715909",
        "Average Auto Demand": "13896948.992903445",
        "Auto Demand %": "-0.007771466771070583",
        "Auto Workforce": "2594.254",
        "Auto Workforce Change": "-0.00419857252731759",
        "Auto Capex Change": "-0.031671465373541485",
        "Auto Supply %": "-0.017935018950429538",
        "Output Gap %": "0.019165393289637695",
        "Output Gap % Mean": "-0.00721527242323511",
        "Output Gap % Stdev": "0.025049042522334197",
        "Output Gap % Strength": "1.0531606423419702"
    },
    {
        "": "65",
        "Date": "2017-06-30",
        "Auto Capex": "4511.0",
        "Retail: Changes in Inventory": "130.0",
        "Manufacturing Workforce": "2680.0",
        "Manufacturing Vacancy Ratio": "2.2",
        "Total Retail Sales": "118081849.0",
        "Other Sales": "14405262.0",
        "Auto Imports": "15594",
        "Auto Exports": "11626",
        "Change in Retail Inventory %": "0.9988990687298605",
        "Average Auto Demand": "14389402.796609648",
        "Auto Demand %": "0.004863649958307274",
        "Auto Workforce": "2621.04",
        "Auto Workforce Change": "0.018729159523792616",
        "Auto Capex Change": "0.0017214397496088107",
        "Auto Supply %": "0.010225299636700713",
        "Output Gap %": "0.022798668908736813",
        "Output Gap % Mean": "-0.0012732658531287321",
        "Output Gap % Stdev": "0.024335919690513356",
        "Output Gap % Strength": "0.9891524572728305"
    },
    {
        "": "66",
        "Date": "2017-09-30",
        "Auto Capex": "4487.0",
        "Retail: Changes in Inventory": "-435.0",
        "Manufacturing Workforce": "2693.0",
        "Manufacturing Vacancy Ratio": "2.1",
        "Total Retail Sales": "118786322.0",
        "Other Sales": "14384324.0",
        "Auto Imports": "15736",
        "Auto Exports": "12290",
        "Change in Retail Inventory %": "1.0036620377891656",
        "Average Auto Demand": "14436999.938059602",
        "Auto Demand %": "0.0025155957573869867",
        "Auto Workforce": "2636.447",
        "Auto Workforce Change": "0.02292605544829507",
        "Auto Capex Change": "0.028354944539915605",
        "Auto Supply %": "0.025640499994105337",
        "Output Gap %": "-0.007709703879313726",
        "Output Gap % Mean": "0.00041135508575093816",
        "Output Gap % Stdev": "0.0230966555332284",
        "Output Gap % Strength": "-0.35161190127207653"
    },
    {
        "": "67",
        "Date": "2017-12-31",
        "Auto Capex": "4478.0",
        "Retail: Changes in Inventory": "-861.0",
        "Manufacturing Workforce": "2699.0",
        "Manufacturing Vacancy Ratio": "2.3000000000000003",
        "Total Retail Sales": "119607419.0",
        "Other Sales": "14676343.0",
        "Auto Imports": "14140",
        "Auto Exports": "12126",
        "Change in Retail Inventory %": "1.0071985501166947",
        "Average Auto Demand": "14781991.390615301",
        "Auto Demand %": "0.02088008005662645",
        "Auto Workforce": "2636.923",
        "Auto Workforce Change": "0.01638387325584767",
        "Auto Capex Change": "0.023623243448537723",
        "Auto Supply %": "0.020003558352192696",
        "Output Gap %": "-0.004760419937478888",
        "Output Gap % Mean": "0.002117007543787489",
        "Output Gap % Stdev": "0.021869961443681748",
        "Output Gap % Strength": "-0.31446911778864944"
    },
    {
        "": "68",
        "Date": "2018-03-31",
        "Auto Capex": "4578.0",
        "Retail: Changes in Inventory": "376.0",
        "Manufacturing Workforce": "2696.0",
        "Manufacturing Vacancy Ratio": "2.3",
        "Total Retail Sales": "118274202.0",
        "Other Sales": "14426204.0",
        "Auto Imports": "15263",
        "Auto Exports": "12580",
        "Change in Retail Inventory %": "0.996820946633823",
        "Average Auto Demand": "14380342.327612644",
        "Auto Demand %": "1.0872802786480543e-05",
        "Auto Workforce": "2633.9919999999997",
        "Auto Workforce Change": "0.004947224248373794",
        "Auto Capex Change": "0.004971801721579183",
        "Auto Supply %": "0.0049595129849764885",
        "Output Gap %": "-0.019992685549406215",
        "Output Gap % Mean": "0.004489062532548942",
        "Output Gap % Stdev": "0.01711665150999443",
        "Output Gap % Strength": "-1.4302883988530257"
    },
    {
        "": "69",
        "Date": "2018-06-30",
        "Auto Capex": "4433.0",
        "Retail: Changes in Inventory": "282.0",
        "Manufacturing Workforce": "2715.0",
        "Manufacturing Vacancy Ratio": "2.4",
        "Total Retail Sales": "120364072.0",
        "Other Sales": "14535449.0",
        "Auto Imports": "15314",
        "Auto Exports": "11837",
        "Change in Retail Inventory %": "0.9976571081775963",
        "Average Auto Demand": "14501394.015402935",
        "Auto Demand %": "0.0017142285553079322",
        "Auto Workforce": "2649.84",
        "Auto Workforce Change": "0.005085746134695479",
        "Auto Capex Change": "-0.00398729971202838",
        "Auto Supply %": "0.0005492232113335493",
        "Output Gap %": "-0.003245284429668556",
        "Output Gap % Mean": "0.0062857725767803945",
        "Output Gap % Stdev": "0.014921244677919117",
        "Output Gap % Strength": "-0.6387575039603286"
    },
    {
        "": "70",
        "Date": "2018-09-30",
        "Auto Capex": "4494.0",
        "Retail: Changes in Inventory": "-306.0",
        "Manufacturing Workforce": "2700.0",
        "Manufacturing Vacancy Ratio": "2.433333333333333",
        "Total Retail Sales": "122083704.0",
        "Other Sales": "14929567.0",
        "Auto Imports": "13688",
        "Auto Exports": "12011",
        "Change in Retail Inventory %": "1.002506477031529",
        "Average Auto Demand": "14966987.616776174",
        "Auto Demand %": "0.00445105431504933",
        "Auto Workforce": "2634.3",
        "Auto Workforce Change": "-0.0009593049071713322",
        "Auto Capex Change": "0.0011861516791460414",
        "Auto Supply %": "0.00011342338598735457",
        "Output Gap %": "0.0039018311037157805",
        "Output Gap % Mean": "0.006534907368263563",
        "Output Gap % Stdev": "0.014851434399608811",
        "Output Gap % Strength": "-0.17729440764436452"
    },
    {
        "": "71",
        "Date": "2018-12-31",
        "Auto Capex": "4822.0",
        "Retail: Changes in Inventory": "-1239.0",
        "Manufacturing Workforce": "2683.0",
        "Manufacturing Vacancy Ratio": "2.5",
        "Total Retail Sales": "122884003.0",
        "Other Sales": "15029551.0",
        "Auto Imports": "15131",
        "Auto Exports": "10501",
        "Change in Retail Inventory %": "1.0100826793541222",
        "Average Auto Demand": "15181089.143569427",
        "Auto Demand %": "0.018276531045386513",
        "Auto Workforce": "2615.9249999999997",
        "Auto Workforce Change": "-0.006823069673624893",
        "Auto Capex Change": "0.01806738245094408",
        "Auto Supply %": "0.005622156388659594",
        "Output Gap %": "0.018163107659399158",
        "Output Gap % Mean": "0.006575139570808108",
        "Output Gap % Stdev": "0.014885729356991588",
        "Output Gap % Strength": "0.7784615594363449"
    },
    {
        "": "72",
        "Date": "2019-03-31",
        "Auto Capex": "4715.0",
        "Retail: Changes in Inventory": "-1138.0",
        "Manufacturing Workforce": "2705.0",
        "Manufacturing Vacancy Ratio": "2.466666666666667",
        "Total Retail Sales": "123972656.0",
        "Other Sales": "15404803.0",
        "Auto Imports": "16750",
        "Auto Exports": "10833",
        "Change in Retail Inventory %": "1.0091794435702015",
        "Average Auto Demand": "15546210.51984857",
        "Auto Demand %": "0.023487600176714363",
        "Auto Workforce": "2638.2766666666666",
        "Auto Workforce Change": "-0.004295332525424911",
        "Auto Capex Change": "0.020510582587824677",
        "Auto Supply %": "0.008107625031199883",
        "Output Gap %": "0.01786544378805477",
        "Output Gap % Mean": "0.006403169128232916",
        "Output Gap % Stdev": "0.014727824582900883",
        "Output Gap % Strength": "0.7782734371462872"
    },
    {
        "": "73",
        "Date": "2019-06-30",
        "Auto Capex": "4647.0",
        "Retail: Changes in Inventory": "2495.0",
        "Manufacturing Workforce": "2689.0",
        "Manufacturing Vacancy Ratio": "2.2666666666666666",
        "Total Retail Sales": "124401958.0",
        "Other Sales": "15636261.0",
        "Auto Imports": "14397",
        "Auto Exports": "10138",
        "Change in Retail Inventory %": "0.9799440455752312",
        "Average Auto Demand": "15322660.86201021",
        "Auto Demand %": "0.007992098547043821",
        "Auto Workforce": "2628.0493333333334",
        "Auto Workforce Change": "-0.0023073479040719436",
        "Auto Capex Change": "0.010904425914047389",
        "Auto Supply %": "0.004298539004987723",
        "Output Gap %": "-0.00011552648415606194",
        "Output Gap % Mean": "0.004607082446952077",
        "Output Gap % Stdev": "0.014265304411375265",
        "Output Gap % Strength": "-0.3310556014032406"
    },
    {
        "": "74",
        "Date": "2019-09-30",
        "Auto Capex": "4344.0",
        "Retail: Changes in Inventory": "-404.0",
        "Manufacturing Workforce": "2694.0",
        "Manufacturing Vacancy Ratio": "2.1333333333333333",
        "Total Retail Sales": "125830054.0",
        "Other Sales": "15526308.0",
        "Auto Imports": "15805",
        "Auto Exports": "11597",
        "Change in Retail Inventory %": "1.0032106796997797",
        "Average Auto Demand": "15576158.001908127",
        "Auto Demand %": "0.00873843838308556",
        "Auto Workforce": "2636.5280000000002",
        "Auto Workforce Change": "0.00789416016094846",
        "Auto Capex Change": "-0.03369994359842077",
        "Auto Supply %": "-0.012902891718736154",
        "Output Gap %": "0.004439899378097837",
        "Output Gap % Mean": "0.0031345330557980915",
        "Output Gap % Stdev": "0.013324537548928284",
        "Output Gap % Strength": "0.09796710148523977"
    },
    {
        "": "75",
        "Date": "2019-12-31",
        "Auto Capex": "4249.0",
        "Retail: Changes in Inventory": "-677.0",
        "Manufacturing Workforce": "2675.0",
        "Manufacturing Vacancy Ratio": "2.1",
        "Total Retail Sales": "124715274.0",
        "Other Sales": "15296890.0",
        "Auto Imports": "14299",
        "Auto Exports": "10717",
        "Change in Retail Inventory %": "1.0054283647727063",
        "Average Auto Demand": "15379927.098807963",
        "Auto Demand %": "-0.0034779696784857927",
        "Auto Workforce": "2618.825",
        "Auto Workforce Change": "-0.0073648123123797316",
        "Auto Capex Change": "-0.03399970815701148",
        "Auto Supply %": "-0.020682260234695604",
        "Output Gap %": "0.00942492204025036",
        "Output Gap % Mean": "0.0017971583689494462",
        "Output Gap % Stdev": "0.011704200348772472",
        "Output Gap % Strength": "0.6517116457341666"
    },
    {
        "": "76",
        "Date": "2020-03-31",
        "Auto Capex": "4378.0",
        "Retail: Changes in Inventory": "-797.0",
        "Manufacturing Workforce": "2676.0",
        "Manufacturing Vacancy Ratio": "2.2666666666666666",
        "Total Retail Sales": "131030054.0",
        "Other Sales": "15091071.0",
        "Auto Imports": "13280",
        "Auto Exports": "9454",
        "Change in Retail Inventory %": "1.00608257400245",
        "Average Auto Demand": "15182863.556133727",
        "Auto Demand %": "-0.002955751957411231",
        "Auto Workforce": "2615.344",
        "Auto Workforce Change": "-0.004817513981799526",
        "Auto Capex Change": "-0.02031722054380669",
        "Auto Supply %": "-0.012567367262803109",
        "Output Gap %": "0.017726508277284374",
        "Output Gap % Mean": "0.0043407795846092554",
        "Output Gap % Stdev": "0.012163508366535548",
        "Output Gap % Strength": "1.1004825490565011"
    },
    {
        "": "77",
        "Date": "2020-06-30",
        "Auto Capex": "4039.0",
        "Retail: Changes in Inventory": "-1049.0",
        "Manufacturing Workforce": "2618.0",
        "Manufacturing Vacancy Ratio": "1.3333333333333333",
        "Total Retail Sales": "110259459.0",
        "Other Sales": "9451890.0",
        "Auto Imports": "5326",
        "Auto Exports": "3380",
        "Change in Retail Inventory %": "1.0095139229732661",
        "Average Auto Demand": "9541814.553411784",
        "Auto Demand %": "-0.13231723731398307",
        "Auto Workforce": "2583.0933333333332",
        "Auto Workforce Change": "-0.02037506324733307",
        "Auto Capex Change": "-0.02351399275306454",
        "Auto Supply %": "-0.021944528000198804",
        "Output Gap %": "-0.11974987005117996",
        "Output Gap % Mean": "-0.007158165426760852",
        "Output Gap % Stdev": "0.041264672208926316",
        "Output Gap % Strength": "-2.728525360733713"
    },
    {
        "": "78",
        "Date": "2020-09-30",
        "Auto Capex": "4122.0",
        "Retail: Changes in Inventory": "601.0",
        "Manufacturing Workforce": "2570.0",
        "Manufacturing Vacancy Ratio": "1.3",
        "Total Retail Sales": "130476573.0",
        "Other Sales": "15985174.0",
        "Auto Imports": "12554",
        "Auto Exports": "8777",
        "Change in Retail Inventory %": "0.9953938091246465",
        "Average Auto Demand": "15911543.237380262",
        "Auto Demand %": "0.0944019727192497",
        "Auto Workforce": "2536.59",
        "Auto Workforce Change": "-0.03166351368387321",
        "Auto Capex Change": "-0.01002684351807992",
        "Auto Supply %": "-0.020845178600976566",
        "Output Gap %": "0.1163465007194485",
        "Output Gap % Mean": "0.006475753200124621",
        "Output Gap % Stdev": "0.05632721745346947",
        "Output Gap % Strength": "1.9505800656687047"
    },
    {
        "": "79",
        "Date": "2020-12-31",
        "Auto Capex": "4054.0",
        "Retail: Changes in Inventory": "1052.0",
        "Manufacturing Workforce": "2556.0",
        "Manufacturing Vacancy Ratio": "1.7666666666666666",
        "Total Retail Sales": "129760186.0",
        "Other Sales": "15699677.0",
        "Auto Imports": "15320",
        "Auto Exports": "9995",
        "Change in Retail Inventory %": "0.9918927366519034",
        "Average Auto Demand": "15572395.584080944",
        "Auto Demand %": "0.09156812870906302",
        "Auto Workforce": "2510.844",
        "Auto Workforce Change": "-0.04048413845071386",
        "Auto Capex Change": "-0.025839381130871697",
        "Auto Supply %": "-0.03316175979079278",
        "Output Gap %": "0.11241330731003958",
        "Output Gap % Mean": "0.018041612374095434",
        "Output Gap % Stdev": "0.06527325013469996",
        "Output Gap % Strength": "1.4457943298548135"
    },
    {
        "": "80",
        "Date": "2021-03-31",
        "Auto Capex": "4167.0",
        "Retail: Changes in Inventory": "1524.0",
        "Manufacturing Workforce": "2537.0",
        "Manufacturing Vacancy Ratio": "2.1",
        "Total Retail Sales": "120839114.0",
        "Other Sales": "12058574.0",
        "Auto Imports": "11490",
        "Auto Exports": "10139",
        "Change in Retail Inventory %": "0.9873881895559082",
        "Average Auto Demand": "11906493.550485946",
        "Auto Demand %": "0.13694487436216451",
        "Auto Workforce": "2483.723",
        "Auto Workforce Change": "-0.03895435690635696",
        "Auto Capex Change": "0.010478919361440742",
        "Auto Supply %": "-0.014237718772458108",
        "Output Gap %": "0.1701066341529573",
        "Output Gap % Mean": "0.03466209267901958",
        "Output Gap % Stdev": "0.08062726890994676",
        "Output Gap % Strength": "1.6798850228353486"
    },
    {
        "": "81",
        "Date": "2021-06-30",
        "Auto Capex": "4229.0",
        "Retail: Changes in Inventory": "-127.0",
        "Manufacturing Workforce": "2544.0",
        "Manufacturing Vacancy Ratio": "2.533333333333333",
        "Total Retail Sales": "133458854.0",
        "Other Sales": "16879190.0",
        "Auto Imports": "12455",
        "Auto Exports": "9417",
        "Change in Retail Inventory %": "1.0009516041550903",
        "Average Auto Demand": "16895252.30733856",
        "Auto Demand %": "0.054089980181982265",
        "Auto Workforce": "2479.552",
        "Auto Workforce Change": "-0.0226307278570006",
        "Auto Capex Change": "0.008668881147208873",
        "Auto Supply %": "-0.006980923354895863",
        "Output Gap %": "0.06832769895444038",
        "Output Gap % Mean": "0.03967855180852371",
        "Output Gap % Stdev": "0.08104615718090386",
        "Output Gap % Strength": "0.3534917402927402"
    },
    {
        "": "82",
        "Date": "2021-09-30",
        "Auto Capex": "4308.0",
        "Retail: Changes in Inventory": "423.0",
        "Manufacturing Workforce": "2537.0",
        "Manufacturing Vacancy Ratio": "3.1333333333333333",
        "Total Retail Sales": "130718172.0",
        "Other Sales": "16606919.0",
        "Auto Imports": "12436",
        "Auto Exports": "8332",
        "Change in Retail Inventory %": "0.9967640306353122",
        "Average Auto Demand": "16553179.518874148",
        "Auto Demand %": "0.054445942068362875",
        "Auto Workforce": "2457.5073333333335",
        "Auto Workforce Change": "-0.02137146555107572",
        "Auto Capex Change": "0.02040160642570288",
        "Auto Supply %": "-0.0004849295626864203",
        "Output Gap %": "0.06142686542325874",
        "Output Gap % Mean": "0.044034693972044105",
        "Output Gap % Stdev": "0.0809140381050643",
        "Output Gap % Strength": "0.21494627951495207"
    },
    {
        "": "83",
        "Date": "2021-12-31",
        "Auto Capex": "4324.0",
        "Retail: Changes in Inventory": "-126.0",
        "Manufacturing Workforce": "2553.0",
        "Manufacturing Vacancy Ratio": "3.9",
        "Total Retail Sales": "130189373.0",
        "Other Sales": "16906963.0",
        "Auto Imports": "12709",
        "Auto Exports": "8273",
        "Change in Retail Inventory %": "1.0009678209295931",
        "Average Auto Demand": "16923325.91264726",
        "Auto Demand %": "0.14036971771985673",
        "Auto Workforce": "2453.433",
        "Auto Workforce Change": "-0.012227831333217143",
        "Auto Capex Change": "0.012358312342569233",
        "Auto Supply %": "6.524050467604514e-05",
        "Output Gap %": "0.14085464728254316",
        "Output Gap % Mean": "0.05813171134871402",
        "Output Gap % Stdev": "0.08456512051256711",
        "Output Gap % Strength": "0.9782157872232417"
    },
    {
        "": "84",
        "Date": "2022-03-31",
        "Auto Capex": "4243.0",
        "Retail: Changes in Inventory": "3372.0",
        "Manufacturing Workforce": "2612.0",
        "Manufacturing Vacancy Ratio": "3.8666666666666667",
        "Total Retail Sales": "127069076.0",
        "Other Sales": "16839670.0",
        "Auto Imports": "13921",
        "Auto Exports": "8464",
        "Change in Retail Inventory %": "0.9734632523809333",
        "Average Auto Demand": "16392799.927221632",
        "Auto Demand %": "-0.009744812570228448",
        "Auto Workforce": "2511.0026666666668",
        "Auto Workforce Change": "0.012916445949132327",
        "Auto Capex Change": "0.0010885623201928318",
        "Auto Supply %": "0.007002504134662579",
        "Output Gap %": "-0.009810053074904493",
        "Output Gap % Mean": "0.05670671610341379",
        "Output Gap % Stdev": "0.08568307432468159",
        "Output Gap % Strength": "-0.776311654344523"
    },
    {
        "": "85",
        "Date": "2022-06-30",
        "Auto Capex": "4482.0",
        "Retail: Changes in Inventory": "2539.0",
        "Manufacturing Workforce": "2612.0",
        "Manufacturing Vacancy Ratio": "3.8666666666666667",
        "Total Retail Sales": "124103171.0",
        "Other Sales": "16169371.0",
        "Auto Imports": "13656",
        "Auto Exports": "8613",
        "Change in Retail Inventory %": "0.9795412157518522",
        "Average Auto Demand": "15838565.327282742",
        "Auto Demand %": "-0.014265797507839073",
        "Auto Workforce": "2511.0026666666668",
        "Auto Workforce Change": "0.021807030484833456",
        "Auto Capex Change": "0.013514563106796107",
        "Auto Supply %": "0.01766079679581478",
        "Output Gap %": "-0.021268301642501652",
        "Output Gap % Mean": "0.053637393735138594",
        "Output Gap % Stdev": "0.08808116899024991",
        "Output Gap % Strength": "-0.8504166808450497"
    },
    {
        "": "86",
        "Date": "2022-09-30",
        "Auto Capex": "4586.0",
        "Retail: Changes in Inventory": "-1554.0",
        "Manufacturing Workforce": "2617.0",
        "Manufacturing Vacancy Ratio": "3.6999999999999997",
        "Total Retail Sales": "122160683.0",
        "Other Sales": "15740274.0",
        "Auto Imports": "13660",
        "Auto Exports": "10306",
        "Change in Retail Inventory %": "1.0127209504878096",
        "Average Auto Demand": "15940505.246218557",
        "Auto Demand %": "-0.019574084579257283",
        "Auto Workforce": "2520.171",
        "Auto Workforce Change": "0.027116207353392152",
        "Auto Capex Change": "0.02007816690934172",
        "Auto Supply %": "0.023597187131366937",
        "Output Gap %": "-0.03723488137507207",
        "Output Gap % Mean": "0.04814125476990295",
        "Output Gap % Stdev": "0.09218986099366865",
        "Output Gap % Strength": "-0.9260903013058934"
    },
    {
        "": "87",
        "Date": "2022-12-31",
        "Auto Capex": "4440.0",
        "Retail: Changes in Inventory": "-1071.0",
        "Manufacturing Workforce": "2621.0",
        "Manufacturing Vacancy Ratio": "3.4",
        "Total Retail Sales": "120964940.0",
        "Other Sales": "15483876.0",
        "Auto Imports": "14267",
        "Auto Exports": "9975",
        "Change in Retail Inventory %": "1.0088538050777358",
        "Average Auto Demand": "15620967.21995183",
        "Auto Demand %": "-0.01580637236112777",
        "Auto Workforce": "2531.886",
        "Auto Workforce Change": "0.008299757967872301",
        "Auto Capex Change": "0.014799789647659933",
        "Auto Supply %": "0.011549773807766117",
        "Output Gap %": "-0.0394035594924947",
        "Output Gap % Mean": "0.056175885825771474",
        "Output Gap % Stdev": "0.07840198833844679",
        "Output Gap % Strength": "-1.2190946600189208"
    },
    {
        "": "88",
        "Date": "2023-03-31",
        "Auto Capex": "4544.0",
        "Retail: Changes in Inventory": "-894.0",
        "Manufacturing Workforce": "2613.0",
        "Manufacturing Vacancy Ratio": "3.266666666666667",
        "Total Retail Sales": "120767956.0",
        "Other Sales": "15222369.0",
        "Auto Imports": "15842",
        "Auto Exports": "9738",
        "Change in Retail Inventory %": "1.0074026259084818",
        "Average Auto Demand": "15335054.50314787",
        "Auto Demand %": "-0.01063753962553493",
        "Auto Workforce": "2527.6420000000003",
        "Auto Workforce Change": "0.006623537158562676",
        "Auto Capex Change": "0.004589872668048667",
        "Auto Supply %": "0.005606704913305671",
        "Output Gap %": "-0.022187313433301048",
        "Output Gap % Mean": "0.042322504410496516",
        "Output Gap % Stdev": "0.07882679487603789",
        "Output Gap % Strength": "-0.818374233599691"
    },
    {
        "": "89",
        "Date": "2023-06-30",
        "Auto Capex": "4689.0",
        "Retail: Changes in Inventory": "47.0",
        "Manufacturing Workforce": "2578.0",
        "Manufacturing Vacancy Ratio": "3.0",
        "Total Retail Sales": "120947942.0",
        "Other Sales": "15300440.0",
        "Auto Imports": "17682",
        "Auto Exports": "11383",
        "Change in Retail Inventory %": "0.999611403061327",
        "Average Auto Demand": "15294494.29585565",
        "Auto Demand %": "-0.013664578926172491",
        "Auto Workforce": "2500.66",
        "Auto Workforce Change": "-0.00770249790893518",
        "Auto Capex Change": "0.007590272660280117",
        "Auto Supply %": "-5.611262432753117e-05",
        "Output Gap %": "-0.01927128383947816",
        "Output Gap % Mean": "0.029154045295544745",
        "Output Gap % Stdev": "0.07678972968012436",
        "Output Gap % Strength": "-0.6306224717386514"
    },
    {
        "": "90",
        "Date": "2023-09-30",
        "Auto Capex": "4543.0",
        "Retail: Changes in Inventory": "-564.0",
        "Manufacturing Workforce": "2599.0",
        "Manufacturing Vacancy Ratio": "2.9333333333333336",
        "Total Retail Sales": "119620704.0",
        "Other Sales": "14988049.0",
        "Auto Imports": "16931",
        "Auto Exports": "11334",
        "Change in Retail Inventory %": "1.0047149028649756",
        "Average Auto Demand": "15058716.195170494",
        "Auto Demand %": "-0.012121317558417832",
        "Auto Workforce": "2522.7626666666665",
        "Auto Workforce Change": "-0.0035122587581261078",
        "Auto Capex Change": "0.007533094419659214",
        "Auto Supply %": "0.0020104178307665532",
        "Output Gap %": "-0.012065204934090301",
        "Output Gap % Mean": "0.010936861386839985",
        "Output Gap % Stdev": "0.059238406880230736",
        "Output Gap % Strength": "-0.3882965044525298"
    },
    {
        "": "91",
        "Date": "2023-12-31",
        "Auto Capex": "4613.0",
        "Retail: Changes in Inventory": "1265.0",
        "Manufacturing Workforce": "2590.0",
        "Manufacturing Vacancy Ratio": "2.8000000000000003",
        "Total Retail Sales": "118753856.0",
        "Other Sales": "15050247.0",
        "Auto Imports": "17686",
        "Auto Exports": "10949",
        "Change in Retail Inventory %": "0.9893477143175882",
        "Average Auto Demand": "14889927.469365139",
        "Auto Demand %": "-0.009756507004278917",
        "Auto Workforce": "2517.48",
        "Auto Workforce Change": "-0.003930038599954444",
        "Auto Capex Change": "0.0050087108013936454",
        "Auto Supply %": "0.0005393361007196007",
        "Output Gap %": "-0.01176692483504547",
        "Output Gap % Mean": "0.002927399007891399",
        "Output Gap % Stdev": "0.05593939025952838",
        "Output Gap % Strength": "-0.2626829462166675"
    },
    {
        "": "92",
        "Date": "2024-03-31",
        "Auto Capex": "4720.0",
        "Retail: Changes in Inventory": "-39.0",
        "Manufacturing Workforce": "2580.0",
        "Manufacturing Vacancy Ratio": "2.766666666666667",
        "Total Retail Sales": "120625366.0",
        "Other Sales": "16172475.0",
        "Auto Imports": "16369",
        "Auto Exports": "11005",
        "Change in Retail Inventory %": "1.0003233150811746",
        "Average Auto Demand": "16177703.805067418",
        "Auto Demand %": "0.019953940188785973",
        "Auto Workforce": "2508.6200000000003",
        "Auto Workforce Change": "0.0032253401816719762",
        "Auto Capex Change": "0.002239075478512209",
        "Auto Supply %": "0.0027322078300920927",
        "Output Gap %": "0.019414604088066372",
        "Output Gap % Mean": "-0.0012738271256278375",
        "Output Gap % Stdev": "0.052531552205099426",
        "Output Gap % Strength": "0.39382866763426627"
    },
    {
        "": "93",
        "Date": "2024-06-30",
        "Auto Capex": "4703.0",
        "Retail: Changes in Inventory": "-680.0",
        "Manufacturing Workforce": "2576.0",
        "Manufacturing Vacancy Ratio": "2.6333333333333333",
        "Total Retail Sales": "119757022.0",
        "Other Sales": "16123497.0",
        "Auto Imports": "15922",
        "Auto Exports": "10380",
        "Change in Retail Inventory %": "1.005678163907583",
        "Average Auto Demand": "16215048.858729422",
        "Auto Demand %": "0.025862042894042186",
        "Auto Workforce": "2508.1653333333334",
        "Auto Workforce Change": "-0.005794634804548671",
        "Auto Capex Change": "0.011530700490054668",
        "Auto Supply %": "0.002868032842752999",
        "Output Gap %": "0.023129835063950093",
        "Output Gap % Mean": "-0.013046308347487146",
        "Output Gap % Stdev": "0.020669887230709935",
        "Output Gap % Strength": "1.7501858141581512"
    },
    {
        "": "94",
        "Date": "2024-09-30",
        "Auto Capex": "4591.0",
        "Retail: Changes in Inventory": "-2732.0",
        "Manufacturing Workforce": "2589.0",
        "Manufacturing Vacancy Ratio": "2.533333333333333",
        "Total Retail Sales": "121386495.0",
        "Other Sales": "16513433.0",
        "Auto Imports": "16507",
        "Auto Exports": "10772",
        "Change in Retail Inventory %": "1.022506622338836",
        "Average Auto Demand": "16885094.60004867",
        "Auto Demand %": "0.04337243232010857",
        "Auto Workforce": "2523.4120000000003",
        "Auto Workforce Change": "0.002378178301270628",
        "Auto Capex Change": "-0.0015673981191222097",
        "Auto Supply %": "0.0004053900910742092",
        "Output Gap %": "0.04050439947735557",
        "Output Gap % Mean": "-0.008014863092261137",
        "Output Gap % Stdev": "0.026769071477611744",
        "Output Gap % Strength": "1.812511973386738"
    },
    {
        "": "95",
        "Date": "2024-12-31",
        "Auto Capex": "4695.0",
        "Retail: Changes in Inventory": "528.0",
        "Manufacturing Workforce": "2607.0",
        "Manufacturing Vacancy Ratio": "2.3333333333333335",
        "Total Retail Sales": "120261474.0",
        "Other Sales": "16911447.0",
        "Auto Imports": "16276",
        "Auto Exports": "9817",
        "Change in Retail Inventory %": "0.9956095665349985",
        "Average Auto Demand": "16837198.417149603",
        "Auto Demand %": "0.013598097974793314",
        "Auto Workforce": "2546.17",
        "Auto Workforce Change": "0.014916312001104548",
        "Auto Capex Change": "-0.0017839303553589536",
        "Auto Supply %": "0.006566190822872797",
        "Output Gap %": "0.013192707883719105",
        "Output Gap % Mean": "-0.004568762139639063",
        "Output Gap % Stdev": "0.027089563397287627",
        "Output Gap % Strength": "0.6556573010378068"
    },
    {
        "": "96",
        "Date": "2025-03-31",
        "Auto Capex": "4598.0",
        "Retail: Changes in Inventory": "-318.0",
        "Manufacturing Workforce": "2590.0",
        "Manufacturing Vacancy Ratio": "2.3000000000000003",
        "Total Retail Sales": "131005731.0",
        "Other Sales": "18141402.0",
        "Auto Imports": "16059",
        "Auto Exports": "9986",
        "Change in Retail Inventory %": "1.0024273747230188",
        "Average Auto Demand": "18185437.98065492",
        "Auto Demand %": "0.03952030668620243",
        "Auto Workforce": "2530.43",
        "Auto Workforce Change": "0.008915719854545756",
        "Auto Capex Change": "-0.007505897490885705",
        "Auto Supply %": "0.0007049111818300258",
        "Output Gap %": "0.032954115863329636",
        "Output Gap % Mean": "0.002450137584201108",
        "Output Gap % Stdev": "0.0267765268262457",
        "Output Gap % Strength": "1.1392059349993544"
    }
]